ir_datasets/__init__.py
ir_datasets/__main__.py
ir_datasets/lazy_libs.py
ir_datasets/log.py
ir_datasets/commands/__init__.py
ir_datasets/commands/build_c4_checkpoints.py
ir_datasets/commands/build_clueweb_warc_indexes.py
ir_datasets/commands/build_download_cache.py
ir_datasets/commands/clean.py
ir_datasets/commands/doc_fifos.py
ir_datasets/commands/export.py
ir_datasets/commands/generate_metadata.py
ir_datasets/commands/list.py
ir_datasets/commands/lookup.py
ir_datasets/datasets/__init__.py
ir_datasets/datasets/antique.py
ir_datasets/datasets/aol_ia.py
ir_datasets/datasets/aquaint.py
ir_datasets/datasets/argsme.py
ir_datasets/datasets/base.py
ir_datasets/datasets/beir.py
ir_datasets/datasets/c4.py
ir_datasets/datasets/car.py
ir_datasets/datasets/clinicaltrials.py
ir_datasets/datasets/clirmatrix.py
ir_datasets/datasets/clueweb09.py
ir_datasets/datasets/clueweb12.py
ir_datasets/datasets/codec.py
ir_datasets/datasets/codesearchnet.py
ir_datasets/datasets/cord19.py
ir_datasets/datasets/cranfield.py
ir_datasets/datasets/csl.py
ir_datasets/datasets/disks45.py
ir_datasets/datasets/dpr_w100.py
ir_datasets/datasets/gov.py
ir_datasets/datasets/gov2.py
ir_datasets/datasets/hc4.py
ir_datasets/datasets/highwire.py
ir_datasets/datasets/istella22.py
ir_datasets/datasets/kilt.py
ir_datasets/datasets/lotte.py
ir_datasets/datasets/medline.py
ir_datasets/datasets/miracl.py
ir_datasets/datasets/mmarco.py
ir_datasets/datasets/mr_tydi.py
ir_datasets/datasets/msmarco_document.py
ir_datasets/datasets/msmarco_document_v2.py
ir_datasets/datasets/msmarco_passage.py
ir_datasets/datasets/msmarco_passage_v2.py
ir_datasets/datasets/msmarco_qna.py
ir_datasets/datasets/natural_questions.py
ir_datasets/datasets/neuclir.py
ir_datasets/datasets/neumarco.py
ir_datasets/datasets/nfcorpus.py
ir_datasets/datasets/nyt.py
ir_datasets/datasets/pmc.py
ir_datasets/datasets/sara.py
ir_datasets/datasets/touche.py
ir_datasets/datasets/touche_image.py
ir_datasets/datasets/trec_arabic.py
ir_datasets-0.5.9.dist-info/LICENSE
ir_datasets-0.5.9.dist-info/METADATA
ir_datasets-0.5.9.dist-info/WHEEL
ir_datasets-0.5.9.dist-info/entry_points.txt
ir_datasets-0.5.9.dist-info/top_level.txt
ir_datasets-0.5.9.dist-info/RECORD
