Metadata-Version: 2.1
Name: ir_datasets
Version: 0.5.9
Summary: provides a common interface to many IR ad-hoc ranking benchmarks, training datasets, etc.
Home-page: https://github.com/allenai/ir_datasets
Author: Sean MacAvaney
Author-email: sean.macavaney@glasgow.ac.uk
Requires-Python: >=3.8
License-File: LICENSE
Requires-Dist: beautifulsoup4>=4.4.1
Requires-Dist: inscriptis>=2.2.0
Requires-Dist: lxml>=4.5.2
Requires-Dist: numpy>=1.18.1
Requires-Dist: pyyaml>=5.3.1
Requires-Dist: requests>=2.22.0
Requires-Dist: tqdm>=4.38.0
Requires-Dist: trec-car-tools>=2.5.4
Requires-Dist: lz4>=3.1.10
Requires-Dist: warc3-wet>=0.2.3
Requires-Dist: warc3-wet-clueweb09>=0.2.5
Requires-Dist: zlib-state>=0.1.3
Requires-Dist: ijson>=3.1.3
Requires-Dist: unlzw3>=0.2.1
